mpd/__init__.py
mpd/asyncio.py
mpd/base.py
mpd/tests.py
mpd/twisted.py
python_mpd2-3.1.1.dist-info/LICENSE.txt
python_mpd2-3.1.1.dist-info/METADATA
python_mpd2-3.1.1.dist-info/WHEEL
python_mpd2-3.1.1.dist-info/top_level.txt
python_mpd2-3.1.1.dist-info/zip-safe
python_mpd2-3.1.1.dist-info/RECORD
