Metadata-Version: 2.1
Name: python-mpd2
Version: 3.1.1
Summary: A Python MPD client library
Home-page: https://github.com/Mic92/python-mpd2
Author: Joerg Thalheim
Author-email: joerg@thalheim.io
License: GNU Lesser General Public License v3 (LGPLv3)
Keywords: mpd
Classifier: Development Status :: 5 - Production/Stable
Classifier: Intended Audience :: Developers
Classifier: License :: OSI Approved :: GNU Library or Lesser General Public License (LGPL)
Classifier: Natural Language :: English
Classifier: Operating System :: OS Independent
Classifier: Programming Language :: Python
Classifier: Programming Language :: Python :: 3
Classifier: Topic :: Software Development :: Libraries :: Python Modules
Requires-Python: >=3.6
License-File: LICENSE.txt
Provides-Extra: twisted
Requires-Dist: Twisted; extra == "twisted"
